fastsklearn/__init__.py
fastsklearn/test.py
fastsklearn-0.0.4.dist-info/LICENSE
fastsklearn-0.0.4.dist-info/METADATA
fastsklearn-0.0.4.dist-info/WHEEL
fastsklearn-0.0.4.dist-info/top_level.txt
fastsklearn-0.0.4.dist-info/RECORD
