Metadata-Version: 2.1
Name: fastsklearn
Version: 0.0.4
Summary: fastsklearn is a package that makes it easy to test different models on different datasets. 
Home-page: https://github.com/rhcproc/fast-sklearn
Author: rhcproc
Author-email: rhcproc@gmail.com
Classifier: Programming Language :: Python :: 3.6
Classifier: Programming Language :: Python :: 3.7
Classifier: Programming Language :: Python :: 3.8
Classifier: Programming Language :: Python :: 3.9
Classifier: Programming Language :: Python :: 3.10
Classifier: License :: OSI Approved :: MIT License
Classifier: Operating System :: OS Independent
Requires-Python: >=3.7
License-File: LICENSE
